load_testing_data_merge_sort/create_chart.py
load_testing_data_merge_sort/generate_data.py
load_testing_data_merge_sort/load_testing_data/1_0.txt
load_testing_data_merge_sort/load_testing_data/2_0.txt
load_testing_data_merge_sort/load_testing_data/3_0.txt
load_testing_data_merge_sort/load_testing_data/4_0.txt
load_testing_data_merge_sort/load_testing_data/5_0.txt
load_testing_data_merge_sort/load_testing_data/6_0.txt
load_testing_data_merge_sort/load_testing_data/7_0.txt
load_testing_data_merge_sort/load_testing_data/8_0.txt
load_testing_data_merge_sort/load_testing_data/9_0.txt
load_testing_data_merge_sort/load_testing_measurements/UNIX TIMESTAMP.csv
load_testing_data_merge_sort/load_testing_plots/UNIX TIMESTAMP.jpg
load_testing_data_merge_sort/measure_time.py
load_testing_data_merge_sort/merge_sort.py
load_testing_data_merge_sort-0.1.0.dist-info/entry_points.txt
load_testing_data_merge_sort-0.1.0.dist-info/WHEEL
load_testing_data_merge_sort-0.1.0.dist-info/METADATA
load_testing_data_merge_sort-0.1.0.dist-info/RECORD
